{"firstName":"Aarnav","lastName":"slfjsdlj","email":"salkdfj@gmail.com","githubUrl":"https://github.com/saarnav890","instagramUrl":"","twitterUrl":"","jobDescription":"jl;k","aboutText":"My name is Aarnav slfjsdlj and I am an asodfjl with a passion for problem-solving, creativity, and collaboration. I have extensive experience with jl;, jlk;, and jl;k, which I have used to develop innovative solutions to a variety of challenges. In addition to my professional experience, I am an avid learner who is always looking for new ways to apply my skills and knowledge. My hobbies, such as jl; and jlk;, have helped me to develop strong communication, problem-solving, and organizational skills. All of these experiences have enabled me to apply my full potential to my current role, and I am confident that I can use my skills to help my team succeed.","projects":["25","27","21","23","20",null,null,null,null,null,null,null,null,null,null,null,null,null,null,null,null,{"title":"ogImageIssue","url":"https://github.com/saarnav890/ogImageIssue","stars":0,"description":null,"language":"TypeScript"},null,{"title":"pert","url":"https://github.com/saarnav890/pert","stars":0,"description":"Siteify Autogenerated Website 🚀","language":"TypeScript"},null,{"title":"practiceProject","url":"https://github.com/saarnav890/practiceProject","stars":0,"description":null,"language":"JavaScript"},null,{"title":"project","url":"https://github.com/saarnav890/project","stars":0,"description":null,"language":"JavaScript"}]}